java_utilities/__init__.py
java_utilities/_entrypoints.py
java_utilities/_jars/__init__.py
java_utilities/_jars/utilities.jar
java_utilities-0.3.0.dist-info/LICENSE
java_utilities-0.3.0.dist-info/METADATA
java_utilities-0.3.0.dist-info/WHEEL
java_utilities-0.3.0.dist-info/entry_points.txt
java_utilities-0.3.0.dist-info/top_level.txt
java_utilities-0.3.0.dist-info/RECORD
